AUTHORS
MANIFEST.in
README.rst
requirements.txt
setup.py
cmd3/__init__.py
cmd3/console.py
cmd3/generate.py
cmd3/setup_management.py
cmd3/shell.py
cmd3/version.py
cmd3/yaml_setup.py
cmd3.egg-info/PKG-INFO
cmd3.egg-info/SOURCES.txt
cmd3.egg-info/dependency_links.txt
cmd3.egg-info/entry_points.txt
cmd3.egg-info/pbr.json
cmd3.egg-info/requires.txt
cmd3.egg-info/top_level.txt
cmd3/etc/__init__.py
cmd3/etc/cmd3.yaml
cmd3/etc/cmd3_template/.gitignore
cmd3/etc/cmd3_template/LICENSE
cmd3/etc/cmd3_template/Makefile
cmd3/etc/cmd3_template/__init__.py
cmd3/etc/cmd3_template/requirements.txt
cmd3/etc/cmd3_template/setup.cfg
cmd3/etc/cmd3_template/setup.py.in
cmd3/etc/cmd3_template/cmd3_template/__init__.py
cmd3/etc/cmd3_template/cmd3_template/command_command.py.in
cmd3/etc/cmd3_template/cmd3_template/plugins/__init__.py
cmd3/etc/cmd3_template/cmd3_template/plugins/cm_shell_command.py.in
cmd3/plugins/__init__.py
cmd3/plugins/activate.py
cmd3/plugins/browser.py
cmd3/plugins/clear.py
cmd3/plugins/edit.py
cmd3/plugins/info.py
cmd3/plugins/load.py
cmd3/plugins/pause.py
cmd3/plugins/py.py
cmd3/plugins/rst.py
cmd3/plugins/script.py
cmd3/plugins/shell_core.py
cmd3/plugins/shell_generate.py
cmd3/plugins/shell_plugins.py
cmd3/plugins/shell_scope.py
cmd3/plugins/template.py
cmd3/plugins/timer.py
cmd3/plugins-example/__init__.py
cmd3/plugins-example/graphviz.py
cmd3/scripts/__init__.py
deprecated/__init__.py
deprecated/setup-orig.py
deprecated/setup.py
fabfile/__init__.py
fabfile/clean.py
fabfile/doc.py
fabfile/security.py