Metadata-Version: 1.1
Name: cmd3
Version: 3.2.0
Summary: cmd3 - A dynamic CMD shell with plugins
Home-page: https://github.com/cloudmesh/cmd3
Author: Gregor von Laszewski
Author-email: laszewski@gmail.com
License: Apache License, Version 2.0
Keywords: cmd commandshell plugins
Platform: UNKNOWN
Classifier: Intended Audience :: Developers
Classifier: Intended Audience :: Education
Classifier: Intended Audience :: Science/Research
Classifier: Development Status :: 5 - Production/Stable
Classifier: Intended Audience :: Developers
Classifier: License :: OSI Approved :: Apache Software License
Classifier: Operating System :: MacOS :: MacOS X
Classifier: Operating System :: POSIX :: Linux
Classifier: Programming Language :: Python :: 2.7
Classifier: Topic :: Scientific/Engineering
Classifier: Topic :: System :: Clustering
Classifier: Topic :: System :: Distributed Computing
Classifier: Topic :: Software Development :: Libraries :: Python Modules
Classifier: Environment :: Console
